MANIFEST.in
README.md
setup.py
djangocms_work/__init__.py
djangocms_work/admin.py
djangocms_work/models.py
djangocms_work/views.py
djangocms_work.egg-info/PKG-INFO
djangocms_work.egg-info/SOURCES.txt
djangocms_work.egg-info/dependency_links.txt
djangocms_work.egg-info/top_level.txt
djangocms_work/migrations/0001_initial.py
djangocms_work/migrations/0002_category_name2.py
djangocms_work/migrations/0003_remove_category_name2.py
djangocms_work/migrations/0004_work_image.py
djangocms_work/migrations/0005_work_youtube_id.py
djangocms_work/migrations/0006_work_home_page.py
djangocms_work/migrations/__init__.py
djangocms_work/templatetags/__init__.py
djangocms_work/templatetags/work_tags.py