Metadata-Version: 1.0
Name: djangocms-work
Version: 0.1
Summary: Companies works small app
Home-page: https://github.com/dmodules/djangocms_work
Author: D-Modules
Author-email: support@d-modules.com
License: GNU General Public License
Platform: UNKNOWN
